setpypi.py
setpypi-0.6.1.dist-info/DESCRIPTION.rst
setpypi-0.6.1.dist-info/METADATA
setpypi-0.6.1.dist-info/RECORD
setpypi-0.6.1.dist-info/WHEEL
setpypi-0.6.1.dist-info/entry_points.txt
setpypi-0.6.1.dist-info/metadata.json
setpypi-0.6.1.dist-info/top_level.txt
