Metadata-Version: 2.0
Name: setpypi
Version: 0.6.1
Summary: setpypi: .pypirc and pip.conf Manager
Home-page: UNKNOWN
Author: wtayyeb
Author-email: w.tayyeb@gmail.com
License: Apache License 2.0
Platform: UNKNOWN
